synnax/__init__.py
synnax/access/__init__.py
synnax/access/policy/__init__.py
synnax/access/policy/client.py
synnax/access/policy/payload.py
synnax/access/role/__init__.py
synnax/access/role/client.py
synnax/access/role/payload.py
synnax/auth.py
synnax/channel/__init__.py
synnax/channel/client.py
synnax/channel/payload.py
synnax/channel/retrieve.py
synnax/channel/writer.py
synnax/cli/__init__.py
synnax/cli/channel.py
synnax/cli/check_timing.py
synnax/cli/connect.py
synnax/cli/console/__init__.py
synnax/cli/console/mock.py
synnax/cli/console/protocol.py
synnax/cli/console/rich.py
synnax/cli/console/sugared.py
synnax/cli/default.py
synnax/cli/flow/__init__.py
synnax/cli/ingest.py
synnax/cli/io.py
synnax/cli/login.py
synnax/cli/populate.py
synnax/cli/synnax.py
synnax/cli/telem.py
synnax/cli/ts_convert.py
synnax/cli/warning.py
synnax/config/__init__.py
synnax/config/clusters.py
synnax/config/file.py
synnax/control/__init__.py
synnax/control/client.py
synnax/control/controller.py
synnax/device/__init__.py
synnax/device/client.py
synnax/device/payload.py
synnax/exceptions.py
synnax/framer/__init__.py
synnax/framer/adapter.py
synnax/framer/client.py
synnax/framer/codec.py
synnax/framer/deleter.py
synnax/framer/frame.py
synnax/framer/iterator.py
synnax/framer/streamer.py
synnax/framer/writer.py
synnax/hardware/__init__.py
synnax/hardware/device/__init__.py
synnax/hardware/labjack/__init__.py
synnax/hardware/modbus/__init__.py
synnax/hardware/ni/__init__.py
synnax/hardware/opcua/__init__.py
synnax/hardware/rack/__init__.py
synnax/hardware/sequence/__init__.py
synnax/hardware/task/__init__.py
synnax/ingest/__init__.py
synnax/ingest/row.py
synnax/io/__init__.py
synnax/io/csv.py
synnax/io/df_converter.py
synnax/io/factory.py
synnax/io/matcher.py
synnax/io/meta.py
synnax/io/protocol.py
synnax/io/tdms.py
synnax/labjack/__init__.py
synnax/labjack/types.py
synnax/modbus/__init__.py
synnax/modbus/types.py
synnax/ni/__init__.py
synnax/ni/types.py
synnax/ontology/__init__.py
synnax-0.49.0.dist-info/METADATA
synnax-0.49.0.dist-info/WHEEL
synnax-0.49.0.dist-info/entry_points.txt
synnax-0.49.0.dist-info/RECORD
