Metadata-Version: 2.4
Name: synnax
Version: 0.49.0
Summary: Synnax Client Library
Keywords: Synnax,Synnax Python Client
Author: Emiliano Bonilla
Author-email: ebonilla@synnaxlabs.com
Requires-Python: >=3.11,<4
Classifier: Programming Language :: Python :: 3
Classifier: Programming Language :: Python :: 3.11
Classifier: Programming Language :: Python :: 3.12
Classifier: Programming Language :: Python :: 3.13
Classifier: Programming Language :: Python :: 3.14
Requires-Dist: alamos (>=0.49.0,<0.50.0)
Requires-Dist: click (>=8.3.0,<9.0.0)
Requires-Dist: keyring (>=25.6.0,<26.0.0)
Requires-Dist: matplotlib (>=3.10.7,<4.0.0)
Requires-Dist: nptdms (>=1.10.0,<2.0.0)
Requires-Dist: numpy (>=2.3.4,<3.0.0)
Requires-Dist: pandas (>=2.3.3,<3.0.0)
Requires-Dist: pydantic (>=2.12.4,<3.0.0)
Requires-Dist: rich (>=14.2.0,<15.0.0)
Requires-Dist: synnax-freighter (>=0.49.0,<0.50.0)
Requires-Dist: urllib3 (>=2.5.0,<3.0.0)
Project-URL: Homepage, https://synnaxlabs.com
Project-URL: Repository, https://github.com/synnaxlabs/synnax
